psptool/__init__.py
psptool/__main__.py
psptool/blob.py
psptool/cert_tree.py
psptool/crypto.py
psptool/directory.py
psptool/entry.py
psptool/errors.py
psptool/fet.py
psptool/file.py
psptool/firmware.py
psptool/header_file.py
psptool/key_store_file.py
psptool/microcode_file.py
psptool/psptool.py
psptool/pubkey_file.py
psptool/rom.py
psptool/utils.py
psptool-3.3.dist-info/METADATA
psptool-3.3.dist-info/WHEEL
psptool-3.3.dist-info/entry_points.txt
psptool-3.3.dist-info/licenses/LICENSE
psptool-3.3.dist-info/RECORD
