Metadata-Version: 2.4
Name: psptool
Version: 3.3
Summary: PSPTool is a tool for dealing with AMD binary blobs
Author-email: Christian Werling <cwerling@posteo.de>
License-File: LICENSE
Requires-Python: >=3.8
Requires-Dist: cryptography>=38.0.0
Requires-Dist: prettytable
